Metadata-Version: 1.2
Name: pyldraw
Version: 0.8.0
Summary: A package for working with LDraw format files.
Home-page: UNKNOWN
Author:  David Boddie <david@boddie.org.uk>
Author-email: rienairefr@gmail.com, david@boddie.org.uk
Maintainer: Matthieu Berthomé <rienafairefr@gmail.com>
License: UNKNOWN
Platform: UNKNOWN
Requires-Python: >=2.7, !=3.0.*, !=3.1.*, !=3.2.*, <3.7
